nexudus/__init__.py
nexudus/nexudus.py
nexudus-0.1.dist-info/DESCRIPTION.rst
nexudus-0.1.dist-info/METADATA
nexudus-0.1.dist-info/RECORD
nexudus-0.1.dist-info/WHEEL
nexudus-0.1.dist-info/metadata.json
nexudus-0.1.dist-info/top_level.txt
