Metadata-Version: 2.0
Name: nexudus
Version: 0.1
Summary: Nexudus API Python Implementation
Home-page: https://github.com/manishgupta24/nexudus-python-api
Author: Manish Gupta
Author-email: manishgupta.ait@gmail.com
License: GNU GPL
Platform: UNKNOWN
